skext/__init__.py
skext/multilabels.py
scikit_extensions-0.1.0.dist-info/LICENSE
scikit_extensions-0.1.0.dist-info/METADATA
scikit_extensions-0.1.0.dist-info/WHEEL
scikit_extensions-0.1.0.dist-info/RECORD
